odoo/addons/pdf_helper/README.rst
odoo/addons/pdf_helper/__init__.py
odoo/addons/pdf_helper/__manifest__.py
odoo/addons/pdf_helper/utils.py
odoo/addons/pdf_helper/i18n/pdf_helper.pot
odoo/addons/pdf_helper/models/__init__.py
odoo/addons/pdf_helper/models/helper.py
odoo/addons/pdf_helper/readme/CONTRIBUTORS.rst
odoo/addons/pdf_helper/readme/DESCRIPTION.rst
odoo/addons/pdf_helper/readme/USAGE.rst
odoo/addons/pdf_helper/static/description/icon.png
odoo/addons/pdf_helper/static/description/index.html
odoo/addons/pdf_helper/tests/__init__.py
odoo/addons/pdf_helper/tests/test_helper.py
odoo/addons/pdf_helper/tests/fixtures/pdf_with_xml_test.pdf
odoo14_addon_pdf_helper-14.0.2.0.1.dist-info/METADATA
odoo14_addon_pdf_helper-14.0.2.0.1.dist-info/WHEEL
odoo14_addon_pdf_helper-14.0.2.0.1.dist-info/top_level.txt
odoo14_addon_pdf_helper-14.0.2.0.1.dist-info/RECORD
