Metadata-Version: 2.1
Name: odoo14-addon-pdf_helper
Version: 14.0.2.0.1
Summary: Provides helpers to work w/ PDFs
Home-page: https://github.com/OCA/edi
Author: Camptocamp, Odoo Community Association (OCA)
Author-email: support@odoo-community.org
License: LGPL-3
Classifier: Programming Language :: Python
Classifier: Framework :: Odoo
Classifier: Framework :: Odoo :: 14.0
Classifier: License :: OSI Approved :: GNU Lesser General Public License v3 (LGPLv3)
Requires-Python: >=3.6
Requires-Dist: odoo <14.1dev,>=14.0a
Requires-Dist: pypdf <5.0,>=3.1.0
